setup.cfg
setup.py
Flask_JSONAPIView.egg-info/PKG-INFO
Flask_JSONAPIView.egg-info/SOURCES.txt
Flask_JSONAPIView.egg-info/dependency_links.txt
Flask_JSONAPIView.egg-info/requires.txt
Flask_JSONAPIView.egg-info/top_level.txt
flask_jsonapiview/__init__.py
flask_jsonapiview/api.py
flask_jsonapiview/authentication.py
flask_jsonapiview/authorization.py
flask_jsonapiview/decorators.py
flask_jsonapiview/exceptions.py
flask_jsonapiview/fields.py
flask_jsonapiview/filtering.py
flask_jsonapiview/meta.py
flask_jsonapiview/pagination.py
flask_jsonapiview/schema.py
flask_jsonapiview/sorting.py
flask_jsonapiview/utils.py
flask_jsonapiview/view.py
flask_jsonapiview/ext/__init__.py
flask_jsonapiview/ext/jwt.py