Metadata-Version: 1.1
Name: Flask-JSONAPIView
Version: 0.1.0
Summary: Building blocks for JSON API endpoints for Flask
Home-page: https://github.com/4Catalyzer/flask-jsonapiview
Author: Jimmy Jia
Author-email: tesrin@gmail.com
License: MIT
Keywords: rest json api flask
Platform: UNKNOWN
Classifier: Development Status :: 2 - Pre-Alpha
Classifier: Framework :: Flask
Classifier: Environment :: Web Environment
Classifier: Intended Audience :: Developers
Classifier: License :: OSI Approved :: MIT License
Classifier: Operating System :: OS Independent
Classifier: Programming Language :: Python
Classifier: Programming Language :: Python :: 2
Classifier: Topic :: Internet :: WWW/HTTP :: Dynamic Content
Classifier: Topic :: Software Development :: Libraries :: Python Modules
